decay_chains/__init__.py
decay_chains/chain_endfb71_pwr.xml
decay_chains/config.py
decay_chains/graph.py
decay_chains/solver.py
decay_chains-0.2.0.dist-info/licenses/LICENSE
decay_chains-0.2.0.dist-info/METADATA
decay_chains-0.2.0.dist-info/WHEEL
decay_chains-0.2.0.dist-info/top_level.txt
decay_chains-0.2.0.dist-info/RECORD
