Metadata-Version: 2.4
Name: decay_chains
Version: 0.2.0
Summary: Calculates radioactive decay chains
Author-email: Jonathan Trieloff <jctrieloff@gmail.com>
License:                     GNU GENERAL PUBLIC LICENSE
Requires-Python: >=3.9
License-File: LICENSE
Requires-Dist: matplotlib
Requires-Dist: treelib
Dynamic: license-file
